{"offers":{"base-checks-azure":{"prices":{"asia-pacific-east":{"value":0.36},"asia-pacific-southeast":{"value":0.36},"australia-east":{"value":0.36},"australia-southeast":{"value":0.36},"brazil-south":{"value":0.36},"canada-central":{"value":0.36},"canada-east":{"value":0.36},"europe-north":{"value":0.36},"europe-west":{"value":0.36},"germany-central":{"value":0.36},"germany-northeast":{"value":0.36},"japan-east":{"value":0.36},"japan-west":{"value":0.36},"uae-central":{"value":0.36},"uae-north":{"value":0.36},"us-central":{"value":0.36},"us-east":{"value":0.36},"us-east-2":{"value":0.36},"usgov-arizona":{"value":0.36},"usgov-iowa":{"value":0.36},"usgov-texas":{"value":0.36},"usgov-virginia":{"value":0.36},"us-north-central":{"value":0.36},"us-south-central":{"value":0.36},"us-west":{"value":0.36}},"pricingTypes":"WebDirect"},"base-checks-external":{"prices":{"asia-pacific-east":{"value":0.54},"asia-pacific-southeast":{"value":0.54},"australia-east":{"value":0.54},"australia-southeast":{"value":0.54},"brazil-south":{"value":0.54},"canada-central":{"value":0.54},"canada-east":{"value":0.54},"europe-north":{"value":0.54},"europe-west":{"value":0.54},"germany-central":{"value":0.54},"germany-northeast":{"value":0.54},"japan-east":{"value":0.54},"japan-west":{"value":0.54},"uae-central":{"value":0.54},"uae-north":{"value":0.54},"us-central":{"value":0.54},"us-east":{"value":0.54},"us-east-2":{"value":0.54},"usgov-arizona":{"value":0.54},"usgov-iowa":{"value":0.54},"usgov-texas":{"value":0.54},"usgov-virginia":{"value":0.54},"us-north-central":{"value":0.54},"us-south-central":{"value":0.54},"us-west":{"value":0.54}},"pricingTypes":"WebDirect"},"fast-checks-azure":{"prices":{"asia-pacific-east":{"value":1.0},"asia-pacific-southeast":{"value":1.0},"australia-east":{"value":1.0},"australia-southeast":{"value":1.0},"brazil-south":{"value":1.0},"canada-central":{"value":1.0},"canada-east":{"value":1.0},"europe-north":{"value":1.0},"europe-west":{"value":1.0},"germany-central":{"value":1.36},"germany-northeast":{"value":1.36},"japan-east":{"value":1.0},"japan-west":{"value":1.0},"uae-central":{"value":1.0},"uae-north":{"value":1.0},"us-central":{"value":1.0},"us-east":{"value":1.0},"us-east-2":{"value":1.0},"usgov-arizona":{"value":1.0},"usgov-iowa":{"value":1.0},"usgov-texas":{"value":1.0},"usgov-virginia":{"value":1.0},"us-north-central":{"value":1.0},"us-south-central":{"value":1.0},"us-west":{"value":1.0}},"pricingTypes":"WebDirect"},"fast-checks-external":{"prices":{"asia-pacific-east":{"value":2.0},"asia-pacific-southeast":{"value":2.0},"australia-east":{"value":2.0},"australia-southeast":{"value":2.0},"brazil-south":{"value":2.0},"canada-central":{"value":2.0},"canada-east":{"value":2.0},"europe-north":{"value":2.0},"europe-west":{"value":2.0},"germany-central":{"value":2.54},"germany-northeast":{"value":2.54},"japan-east":{"value":2.0},"japan-west":{"value":2.0},"uae-central":{"value":2.0},"uae-north":{"value":2.0},"us-central":{"value":2.0},"us-east":{"value":2.0},"us-east-2":{"value":2.0},"usgov-arizona":{"value":2.0},"usgov-iowa":{"value":2.0},"usgov-texas":{"value":2.0},"usgov-virginia":{"value":2.0},"us-north-central":{"value":2.0},"us-south-central":{"value":2.0},"us-west":{"value":2.0}},"pricingTypes":"WebDirect"},"traffic-view":{"prices":{"asia-pacific-east":{"value":2.0},"asia-pacific-southeast":{"value":2.0},"australia-east":{"value":2.0},"australia-southeast":{"value":2.0},"brazil-south":{"value":2.0},"canada-central":{"value":2.0},"canada-east":{"value":2.0},"europe-north":{"value":2.0},"europe-west":{"value":2.0},"germany-central":{"value":2.0},"germany-northeast":{"value":2.0},"japan-east":{"value":2.0},"japan-west":{"value":2.0},"uae-central":{"value":2.0},"uae-north":{"value":2.0},"us-central":{"value":2.0},"us-east":{"value":2.0},"us-east-2":{"value":2.0},"usgov-arizona":{"value":2.0},"usgov-iowa":{"value":2.0},"usgov-texas":{"value":2.0},"usgov-virginia":{"value":2.0},"us-north-central":{"value":2.0},"us-south-central":{"value":2.0},"us-west":{"value":2.0}},"pricingTypes":"WebDirect"},"user-measurements":{"prices":{"asia-pacific-east":{"value":2.0},"asia-pacific-southeast":{"value":2.0},"australia-east":{"value":2.0},"australia-southeast":{"value":2.0},"brazil-south":{"value":2.0},"canada-central":{"value":2.0},"canada-east":{"value":2.0},"europe-north":{"value":2.0},"europe-west":{"value":2.0},"germany-central":{"value":2.0},"germany-northeast":{"value":2.0},"japan-east":{"value":2.0},"japan-west":{"value":2.0},"uae-central":{"value":2.0},"uae-north":{"value":2.0},"us-central":{"value":2.0},"us-east":{"value":2.0},"us-east-2":{"value":2.0},"usgov-arizona":{"value":2.0},"usgov-iowa":{"value":2.0},"usgov-texas":{"value":2.0},"usgov-virginia":{"value":2.0},"us-north-central":{"value":2.0},"us-south-central":{"value":2.0},"us-west":{"value":2.0}},"pricingTypes":"WebDirect"}},"graduatedOffers":{"dns-queries":{"asia-pacific-east":{"prices":[{"limit":1000.0,"price":{"value":0.54}},{"limit":1.7976931348623157E+308,"price":{"value":0.375}}],"pricingTypes":"WebDirect"},"asia-pacific-southeast":{"prices":[{"limit":1000.0,"price":{"value":0.54}},{"limit":1.7976931348623157E+308,"price":{"value":0.375}}],"pricingTypes":"WebDirect"},"australia-east":{"prices":[{"limit":1000.0,"price":{"value":0.54}},{"limit":1.7976931348623157E+308,"price":{"value":0.375}}],"pricingTypes":"WebDirect"},"australia-southeast":{"prices":[{"limit":1000.0,"price":{"value":0.54}},{"limit":1.7976931348623157E+308,"price":{"value":0.375}}],"pricingTypes":"WebDirect"},"brazil-south":{"prices":[{"limit":1000.0,"price":{"value":0.54}},{"limit":1.7976931348623157E+308,"price":{"value":0.375}}],"pricingTypes":"WebDirect"},"canada-central":{"prices":[{"limit":1000.0,"price":{"value":0.54}},{"limit":1.7976931348623157E+308,"price":{"value":0.375}}],"pricingTypes":"WebDirect"},"canada-east":{"prices":[{"limit":1000.0,"price":{"value":0.54}},{"limit":1.7976931348623157E+308,"price":{"value":0.375}}],"pricingTypes":"WebDirect"},"europe-north":{"prices":[{"limit":1000.0,"price":{"value":0.54}},{"limit":1.7976931348623157E+308,"price":{"value":0.375}}],"pricingTypes":"WebDirect"},"europe-west":{"prices":[{"limit":1000.0,"price":{"value":0.54}},{"limit":1.7976931348623157E+308,"price":{"value":0.375}}],"pricingTypes":"WebDirect"},"germany-central":{"prices":[{"limit":1000.0,"price":{"value":0.54}},{"limit":1.7976931348623157E+308,"price":{"value":0.375}}],"pricingTypes":"WebDirect"},"germany-northeast":{"prices":[{"limit":1000.0,"price":{"value":0.54}},{"limit":1.7976931348623157E+308,"price":{"value":0.375}}],"pricingTypes":"WebDirect"},"japan-east":{"prices":[{"limit":1000.0,"price":{"value":0.54}},{"limit":1.7976931348623157E+308,"price":{"value":0.375}}],"pricingTypes":"WebDirect"},"japan-west":{"prices":[{"limit":1000.0,"price":{"value":0.54}},{"limit":1.7976931348623157E+308,"price":{"value":0.375}}],"pricingTypes":"WebDirect"},"uae-central":{"prices":[{"limit":1000.0,"price":{"value":0.54}},{"limit":1.7976931348623157E+308,"price":{"value":0.375}}],"pricingTypes":"WebDirect"},"uae-north":{"prices":[{"limit":1000.0,"price":{"value":0.54}},{"limit":1.7976931348623157E+308,"price":{"value":0.375}}],"pricingTypes":"WebDirect"},"us-central":{"prices":[{"limit":1000.0,"price":{"value":0.54}},{"limit":1.7976931348623157E+308,"price":{"value":0.375}}],"pricingTypes":"WebDirect"},"us-east":{"prices":[{"limit":1000.0,"price":{"value":0.54}},{"limit":1.7976931348623157E+308,"price":{"value":0.375}}],"pricingTypes":"WebDirect"},"us-east-2":{"prices":[{"limit":1000.0,"price":{"value":0.54}},{"limit":1.7976931348623157E+308,"price":{"value":0.375}}],"pricingTypes":"WebDirect"},"usgov-arizona":{"prices":[{"limit":1000.0,"price":{"value":0.54}},{"limit":1.7976931348623157E+308,"price":{"value":0.375}}],"pricingTypes":"WebDirect"},"usgov-iowa":{"prices":[{"limit":1000.0,"price":{"value":0.54}},{"limit":1.7976931348623157E+308,"price":{"value":0.375}}],"pricingTypes":"WebDirect"},"usgov-texas":{"prices":[{"limit":1000.0,"price":{"value":0.54}},{"limit":1.7976931348623157E+308,"price":{"value":0.375}}],"pricingTypes":"WebDirect"},"usgov-virginia":{"prices":[{"limit":1000.0,"price":{"value":0.54}},{"limit":1.7976931348623157E+308,"price":{"value":0.375}}],"pricingTypes":"WebDirect"},"us-north-central":{"prices":[{"limit":1000.0,"price":{"value":0.54}},{"limit":1.7976931348623157E+308,"price":{"value":0.375}}],"pricingTypes":"WebDirect"},"us-south-central":{"prices":[{"limit":1000.0,"price":{"value":0.54}},{"limit":1.7976931348623157E+308,"price":{"value":0.375}}],"pricingTypes":"WebDirect"},"us-west":{"prices":[{"limit":1000.0,"price":{"value":0.54}},{"limit":1.7976931348623157E+308,"price":{"value":0.375}}],"pricingTypes":"WebDirect"}}},"regions":[{"slug":"asia-pacific-east","displayName":"East Asia"},{"slug":"asia-pacific-southeast","displayName":"Southeast Asia"},{"slug":"australia-east","displayName":"Australia East"},{"slug":"australia-southeast","displayName":"Australia Southeast"},{"slug":"brazil-south","displayName":"Brazil South"},{"slug":"canada-central","displayName":"Canada Central"},{"slug":"canada-east","displayName":"Canada East"},{"slug":"europe-north","displayName":"North Europe"},{"slug":"europe-west","displayName":"West Europe"},{"slug":"germany-central","displayName":"Germany Central"},{"slug":"germany-northeast","displayName":"Germany Northeast"},{"slug":"japan-east","displayName":"Japan East"},{"slug":"japan-west","displayName":"Japan West"},{"slug":"us-central","displayName":"Central US"},{"slug":"us-east","displayName":"East US"},{"slug":"us-east-2","displayName":"East US 2"},{"slug":"us-north-central","displayName":"North Central US"},{"slug":"us-south-central","displayName":"South Central US"},{"slug":"us-west","displayName":"West US"},{"slug":"usgov-arizona","displayName":"US Gov Arizona"},{"slug":"usgov-iowa","displayName":"US Gov Iowa"},{"slug":"usgov-texas","displayName":"US Gov Texas"},{"slug":"usgov-virginia","displayName":"US Gov Virginia"},{"slug":"uae-central","displayName":"UAE Central"},{"slug":"uae-north","displayName":"UAE North"}],"discounts":[],"resources":{"endpoints":"Endpoints","millions_per_month":"Millions/mo","traffic_view":"Traffic View","healthchecks":"Health Checks","region":"Region","dnsqueries":"DNS Queries","real_user_measurements_tooltip":"Traffic Manager Real User Measurements currently supports measuring only Azure regions.","external":"External","real_user_measurements":"Real User Measurements","azure":"Azure","fast_interval_health_checks_external":"Fast Interval Health Checks Add-on (External)","fast_interval_health_checks_external_note":"Fast endpoint health checks need to be purchased as an add-on to basic endpoint health checks.","fast_interval_health_checks_azure":"Fast Interval Health Checks Add-on (Azure)","monitored_endpoint":"Monitored endpoint/mo","per_million":"Per million","fast_interval_health_checks_azure_note":"Fast endpoint health checks need to be purchased as an add-on to basic endpoint health checks.","sub_total":"Sub-total","summary_7":"{0} million DNS queries/mo, {1} Azure endpoint(s), {2} Fast Azure endpoint(s), {3}  External endpoint(s), {4} Fast External endpoint(s), {5} million(s) of user measurements, {6} million(s) of data points processed."},"schema":{"serviceSlug":"traffic-manager","version":"v1.0.4","region":"us-east","queries":0,"azureChecks":0,"fastAzureChecks":0,"externalChecks":0,"fastExternalChecks":0,"realUserMeasurements":0,"trafficDataPoints":0,"displayName":"","isCollapsed":false,"isBreakingChange":false,"total":0.0}}